demos/__init__.py
demos/demo.py
serviceCove/Connection.py
serviceCove/Processors.py
serviceCove/__init__.py
serviceCove/client.py
serviceCove/dto.py
serviceCove/executes.py
serviceCove/sayhello.py
serviceCove/server.py
serviceCove/SDG1/__init__.py
serviceCove/SDG1/serviceCove.py
serviceCove/SDG3/__init__.py
serviceCove/SDG3/hospitalCove.py
serviceCove/SDG4/__init__.py
serviceCove/SDG4/educateCove.py
serviceCove/SDG6/__init__.py
serviceCove/SDG6/waterQuality.py
serviceCCOVE-0.1.2.dist-info/LICENSE
serviceCCOVE-0.1.2.dist-info/METADATA
serviceCCOVE-0.1.2.dist-info/WHEEL
serviceCCOVE-0.1.2.dist-info/top_level.txt
serviceCCOVE-0.1.2.dist-info/RECORD
