Metadata-Version: 2.1
Name: serviceCCOVE
Version: 0.1.2
Summary: My short description for my project.
Home-page: https://gitee.com/Jiongbin0202/demo
Author: Jiongbin0202
Author-email: c2218239@163.com
License: MIT
Classifier: License :: OSI Approved :: MIT License
Classifier: Programming Language :: Python
Classifier: Programming Language :: Python :: 3
Classifier: Programming Language :: Python :: 3.6
Classifier: Programming Language :: Python :: Implementation :: CPython
Classifier: Programming Language :: Python :: Implementation :: PyPy
Requires-Python: >=3.6.0
License-File: LICENSE
Requires-Dist: websocket
Requires-Dist: asyncio
Requires-Dist: websockets
